assignment 1/halfbitadder/assignment 1/fullbitadder/fbd.v
module fba(a,b,cin,co,z);
input a;
input b;
input cin;
output z;
output co;
assign z= (a^b)^cin;
assign co= ( a & b) | (( a ^ b) & cin);

endmodule

assignment 1/halfbitadder/assignment 1/fullbitadder/tb_fbd.v
`timescale 1ns/1ns
`include "fbd.v"

module tb_fbd;
fba here(.a(A),.b(B),.cin(CIN),.co(CO),.z(Z));

reg A;
reg B;
reg CIN;
wire CO;
wire Z;

initial begin
 $dumpfile("tb_fbd.vcd");
 $dumpvars(0,here);
 #20
  A=0;
   B=0;
 CIN=0;
  #20;
  $display("%0d %0d %0d %0d %0d",A,B,CIN,Z,CO);
  #20
  A=1; B=0;CIN=0;
  #20;
  $display("%0d %0d %0d %0d %0d",A,B,CIN,Z,CO);
  #20
  A=0; B=1;CIN=0;
  #20;
  $display("%0d %0d %0d %0d %0d",A,B,CIN,Z,CO);
  #20
  A=0; B=0;CIN=1;
  #20;
  $display("%0d %0d %0d %0d %0d",A,B,CIN,Z,CO);
  #20
  A=1; B=1;CIN=0;
  #20;
  $display("%0d %0d %0d %0d %0d",A,B,CIN,Z,CO);
  #20
  A=1; B=0;CIN=1;
  #20;
  $display("%0d %0d %0d %0d %0d",A,B,CIN,Z,CO);
  #20
  A=0; B=1;CIN=1;
  #20;
  $display("%0d %0d %0d %0d %0d",A,B,CIN,Z,CO);
  #20
  A=1; B=1;CIN=1;
  #20;
  $display("%0d %0d %0d %0d %0d",A,B,CIN,Z,CO);
  #20
  $display("Done.");

end

endmodule

assignment 1/halfbitadder/assignment 1/fullbitadder/tb_fbd.vcd
$date
	Fri Jun 03 01:46:44 2022
$end
$version
	Icarus Verilog
$end
$timescale
	1ns
$end
$scope module tb_fbd $end
$scope module here $end
$var wire 1 ! a $end
$var wire 1 " b $end
$var wire 1 # cin $end
$var wire 1 $ co $end
$var wire 1 % z $end
$upscope $end
$upscope $end
$enddefinitions $end
#0
$dumpvars
x%
x$
x#
x"
x!
$end
#20
0$
0%
0#
0"
0!
#60
1%
1!
#100
1"
0!
#140
1#
0"
#180
1$
0%
0#
1"
1!
#220
1#
0"
#260
1"
0!
#300
1%
1!
